piwebasync/__init__.py
piwebasync/__version__.py
piwebasync/exceptions.py
piwebasync/types.py
piwebasync/api/__init__.py
piwebasync/api/models.py
piwebasync/api/util.py
piwebasync/api/controllers/__init__.py
piwebasync/api/controllers/assetdatabases.py
piwebasync/api/controllers/assetservers.py
piwebasync/api/controllers/attributes.py
piwebasync/api/controllers/dataservers.py
piwebasync/api/controllers/elements.py
piwebasync/api/controllers/eventframes.py
piwebasync/api/controllers/points.py
piwebasync/api/controllers/streams.py
piwebasync/api/controllers/streamsets.py
piwebasync/http/__init__.py
piwebasync/http/client.py
piwebasync/http/hooks.py
piwebasync/http/safeurl.py
piwebasync/websockets/__init__.py
piwebasync/websockets/client.py
piwebasync-0.1.2.dist-info/LICENSE
piwebasync-0.1.2.dist-info/METADATA
piwebasync-0.1.2.dist-info/WHEEL
piwebasync-0.1.2.dist-info/top_level.txt
piwebasync-0.1.2.dist-info/RECORD
