Metadata-Version: 2.1
Name: piwebasync
Version: 0.1.2
Summary: An asynchronous client API for interfacing with OSIsoft PI Web API
Home-page: https://github.com/newvicx/piwebasync
Author: Chris Newville
Author-email: chrisnewville1396@gmail.com
License: MIT
Project-URL: Changelog, https://github.com/newvicx/piwebasync/blob/master/CHANGELOG.md
Project-URL: Source, https://github.com/newvicx/piwebasync
Platform: UNKNOWN
Classifier: Development Status :: 4 - Beta
Classifier: Environment :: Web Environment
Classifier: Intended Audience :: Developers
Classifier: License :: OSI Approved :: MIT License
Classifier: Operating System :: Microsoft :: Windows
Classifier: Topic :: Internet :: WWW/HTTP
Classifier: Framework :: AsyncIO
Classifier: Programming Language :: Python :: 3
Classifier: Programming Language :: Python :: 3.9
Classifier: Programming Language :: Python :: 3.10
Classifier: Programming Language :: Python :: 3 :: Only
Requires-Python: >=3.9
License-File: LICENSE
Requires-Dist: async-negotiate-sspi (>=0.1.2)
Requires-Dist: httpx-extensions (>=0.1.1)
Requires-Dist: orjson (>=3.6)
Requires-Dist: pydantic (>=1.9.0)
Requires-Dist: ws-auth (>=0.0.1)
